lucas/__init__.py
lucas-0.0.1.dist-info/LICENSE
lucas-0.0.1.dist-info/METADATA
lucas-0.0.1.dist-info/WHEEL
lucas-0.0.1.dist-info/top_level.txt
lucas-0.0.1.dist-info/RECORD
